Workbook

Sheet Осн. параметры 
B3: Работа | C3: Генподряд
B4: Компенсация роста стоимости материалов | C4: БСМ5%
B5: Аванс | C5: Аванс 30%
B6: Срок строитльства | C6: 24
B7: Срок на передачу объекта | C7: 3
B8: Дата отправки КП | C8: 46232
B12: Работа | C12: Коробка
B13: Компенсация роста стоимости материалов | C13: БСМ5%
B14: Аванс | C14: Аванс 30%
B15: Срок строитльства | C15: 24
B16: Срок на передачу объекта | C16: 3
B17: Дата отправки КП | C17: 46233

Sheet Сущ. условия Генподряд
A1: СУЩЕСТВЕННЫЕ УСЛОВИЯ ГЕНПОДРЯДА:
A3: № | B3: Сроки выполнения работ | C3: Предлагаемые условия СУ-10 | D3: Комментарии Заказчика
A4: 1 | B4: Цена Договора | C4: Твердая договорная цена (см. пункт 7. Существенных условий)
A5: 2 | B5: Ед. измерения в сметной документации | C5: Сметы составляются с ед. измерения этажи/секции или комплексом работ.
A6: 3 | B6: Коммунальные платежи и содержание стройплощадки | C6: 1. В цену входят коммунальные платежи на период с начала производства работ до истечения срока, указанного в п.9. После этого периода - компенсация коммунальных платежей за Заказчиком, включая отопление. 2. В случае продления срока производства работ (не по вине Генподрядчика) Заказчик компенсирует расходы Генподрядчику на содержание стройплощадки в размере 25 млн рублей за каждый дополнительный месяц (в данную стоимость не входят коммунальные платежи).
A7: 4 | B7: Инструкция по эксплуатации Здания | C7: Генеральный подрядчик предоставляет инструкцию по эксплуатации здания (Приложение №6). После ввода объекта в эксплуатацию, управляющая компания обязана строго следовать указанным в инструкции рекомендациям и правилам. В случае нарушения управляющей компанией условий эксплуатации, предусмотренных в инструкции, ответственность за возможные последствия, включая аннулирование гарантий на объект, переходит на управляющую компанию.
A8: 5 | B8: Порядок устранения выявленных недостатков/дефектов | C8: Заказчик обязан соблюдать установленный Договором порядок устранения выявленных недостатков/дефектов силами Генподрядчика. В случае нарушения установленного порядка со стороны Заказчика либо третьих лиц (участников долевого строительства), расходы Заказчика на устранение недостатков/дефектов (возмещение Заказчиком затрат участникам долевого строительства) Генподрядчик не компенсирует.
A9: 6 | B9: Авансы | C9: {=_xlfn.SWITCH('Осн. параметры '!C5,'Сущ. условия (текст)'!D14,'Сущ. условия (текст)'!E14,'Сущ. условия (текст)'!D15,'Сущ. условия (текст)'!E15,'Сущ. условия (текст)'!D16,'Сущ. условия (текст)'!E16)} -> Общий аванс - 30%. Допустимо 5% на аванс под БГ и 25% по распред. письмам за материалы без БГ. Аванс 5% выплачиваются на обычный расчетный счет с предоставлением Банковской гарантии.
A10: 7 | B10: Условия изменения договорной цены | C10: {=_xlfn.SWITCH('Осн. параметры '!C4,'Сущ. условия (текст)'!D4,'Сущ. условия (текст)'!F4,'Сущ. условия (текст)'!D5,'Сущ. условия (текст)'!F5,'Сущ. условия (текст)'!D6,'Сущ. условия (текст)'!F6,'Сущ. условия (текст)'!D7,'Сущ. условия (текст)'!F7,'Сущ. условия (текст)'!D8,'Сущ. условия (текст)'!F8,'Сущ. условия (текст)'!D9,'Сущ. условия (текст)'!F9,'Сущ. условия (текст)'!D10,'Сущ. условия (текст)'!F10,'Сущ. условия (текст)'!D11,'Сущ. условия (текст)'!F11,)} -> 1. Рост стоимости материалов более 5%. Компенсация производится с 6-ого процента. 2. Внесения Заказчиком по своей инициативе изменений в Проектную документацию и/или Рабочую документацию и/или Техническое задание и/или Дизайн проект, Вендор лист предусматривающих изменение объема, состава и/или содержания Работ и/или наименование материала. 3. В случае изменения ставки НДС, стоимость профинансированных (в т.ч. посредством оплаты авансовых платежей) работ рассчитывается по ставке НДС, действовавшей на дату финансирования соответствующих работ, а стоимость не профинансированных работ подлежит изменению с учетом новой ставки НДС посредством подписания дополнительного соглашения к настоящему Договору.
A11: 8 | B11: Компенсация роста стоимости материалов | C11: {=_xlfn.SWITCH('Осн. параметры '!C4,'Сущ. условия (текст)'!D4,'Сущ. условия (текст)'!E4,'Сущ. условия (текст)'!D5,'Сущ. условия (текст)'!E5,'Сущ. условия (текст)'!D6,'Сущ. условия (текст)'!E6,'Сущ. условия (текст)'!D7,'Сущ. условия (текст)'!E7,'Сущ. условия (текст)'!D8,'Сущ. условия (текст)'!E8,'Сущ. условия (текст)'!D9,'Сущ. условия (текст)'!E9,'Сущ. условия (текст)'!D10,'Сущ. условия (текст)'!E10,'Сущ. условия (текст)'!D11,'Сущ. условия (текст)'!E11)} -> Компенсация роста стоимости материалов выполняется по следующему механизму: В стоимости Работ учтен рост стоимости материалов 5%. В случае, если рыночная цена изменится по отношению к базовой стоимости материалов (БСМ) (Приложение №5), актуальной на 29.07.2026 года, более, чем на 5%, то с 6% будет проведен перерасчет стоимости ресурсов между Заказчиком и Генеральным подрядчиком по Методике, изложенной в Приложении №4. Данный процесс предусматривает согласование новых цен и оформление Протоколов изменений, которые могут повлечь за собой корректировку стоимости в рамках договора.
A12: 9 | B12: Сроки выполнения работ | C12: ='Сущ. условия (текст)'!E20 -> Срок выполнения работ составляет 24 мес. до оформления Акта ЗОС и 3 мес. на передачу объекта и подписание Итогового акта №3
A13: 10 | B13: Банковские гарантии | C13: 1. Банковская гарантия обеспечения исполнения Работ (Performance bond, %) - не предоставляется. 2. Банковская гарантия Гарантийного периода - предоставляется: - Сумма БГ соответствует сумме ГУ, удержанного за соответствующий квартал. - Срок действия БГ — на 12 месяцев превышает дату окончания работ по Договору (дату подписания Итогового акта).
A14: 11 | B14: Гарантийные удержания | C14: Гарантийное удержание – 2% Возврат гарантийного удержания: - Поэтапный возврат ГУ — в течение 5 рабочих дней после предоставления Генподрядчиком банковской гарантии (БГ) на исполнение гарантийных обязательств по итогам каждого отчетного квартала (3 календарных месяца выполнения работ).
A15: 12 | B15: Гарантийный срок | C15: Гарантийный период на выполненные работы и установленное оборудование начинается с момента наступления одного из следующих условий, в зависимости от того, что произойдет ранее: 1. получения Заказчиком разрешения на ввод объекта в эксплуатацию (РВ); 2. истечения трех месяцев со дня получения (ЗОС); 3. подписания итогового акта сдачи-приемки выполненных работ. Сроки гарантийного периода: ● Общестроительные работы, включая конструктивные элементы, фасады и кровлю - 36 месяцев ● Инженерные системы и оборудование - 36 месяцев, если предусмотрен гарантийный срок от завода-изготовителя, на эти системы или оборудование применяется срок завода-изготовителя ● Отделочные работы и благоустройство - 24 месяца
A16: 13 | B16: Временное помещение для гарантийного обслуживания | C16: Заказчик предоставляет Генподрядчику на безвозмездной основе помещение сроком на 18 (восемнадцать) месяцев с момента получения заключения о соответствии (ЗОС) для размещения материалов, оборудования и персонала в целях гарантийного обслуживания. Параметры помещения согласовываются Сторонами дополнительно, а по истечении срока либо досрочном прекращении обязательств Генподрядчик возвращает помещение Заказчику в надлежащем состоянии.
A17: 14 | B17: Окончательная приемка работ | C17: Приемка работ в три этапа: ● Акт №1 (для папки ЗОС) - подписываем перед ЗОСом; ● Акт №2 (с исчерпывающим перечнем дефектов) ● Акт №3 - Итоговый Акт после устранения дефектов по Акту №2
A18: 15 | B18: Работы, не предусмотренные в данном Договоре
A22: 16 | B22: К вниманию Заказчика
A27: 17 | B27: Исполнительная документация | C27: Каникулы по ИД на 1 мес, кроме чек листов и 7-ми суточных лабораторных заключений. Исполнительная документация оформляется Генподрядчиком в виде электронных документов в среде общих данных (СОД). В качестве СОД используется программный комплекс HARDROLLER.
A28: 18 | B28: Штрафные санкции для Генерального подрядчика | C28: Общий лимит ответственности по неустойкам – 3% от Цены Работ. Перечень ключевых событий, за которые полагаются штрафы: 1. Завершение работ нулевого цикла; 2. Завершение работ по монолиту надземной части; 3. Закрытие теплового контура; 4. Завершение работ по ВИС; 5. Завершение работ по чистовой отделки; 6. Завершение работ по благоустройству; 7. ЗОС; 8. Итоговый акт; Все штрафы за сроки с 31 дня. Штрафы подлежат учету, но не удерживаются, при этом в случае получения ЗОС вовремя, вся сумма штрафов аннулируется. При этом под практическим завершением по каждому из Ключевых событий подразумевается выполнение Генподрядчиком работ в объеме, достаточном для выполнения последующих видов работ и начала их использования, с возможным наличием технологических проемов и отверстий, необходимых для осуществления прочих видов работ по Договору.
A29: 19 | B29: Уведомление о внесении изменений в документацию | C29: Заказчик не позднее чем за 90 дней до начала работ обязан предупредить генподрядчика о планируемых изменениях в ПД, РД, Техническое задание, Вендор-лист и иную сопутствующую документацию. В случае не уведомления в предусмотренный договором срок Заказчик обязуется компенсировать генподрядчику понесенные расходы.
A30: 20 | B30: Внесение изменений в исходную документацию | C30: При внесении изменений в исходные данные по инициативе любой из Сторон возникающая при этом экономия распределяется между Генподрядчиком и Заказчиком в равных долях (50/50)
A31: 21 | B31: Условия с номинированными Материалами и начисления генподрядного процента: | C31: В случае удорожания/удешевления компенсировать разницу с учетом коэффициента отходов (раскрой, усушка, утряска) + 5% на рост стоимости материалов
A32: 22 | B32: Условия подряда с номинированнными Подрядчиками и начисления генподрядного процента: | C32: Генподрядчик соглашается заключить Договор субподряда с номинированным Подрядчиком на условиях, предусмотренных в Коммерческом предложении Подрядчика. Цены, указанные в Коммерческом предложении, должны включать все затраты на выполнение работ, включая оплату коммунальных услуг и другие связанные расходы. Генподрядчик начисляет генподрядный процент следующим образом: а) Генподрядчик начисляет генподрядный процент в размере 12%, если он не несет ответственности за возврат неиспользованных авансов, предоставленных Подрядчику, за качество, полноту и правильность исполнительной документации, предоставленной Подрядчиком, а также за дефекты в работе, выявленные в гарантийном периоде. В этом случае Генподрядчик обязуется обеспечивать общее управление ходом выполнения работ и предоставлять Подрядчику необходимую документацию и места для производства работ. б) Генподрядчик начисляет генподрядный процент в размере 26%, если он принимает на себя ответственность за использование авансов, выданных Подрядчику, за качество и полноту исполнительной документации, а также за дефекты в работе, выявленные в гарантийном периоде. Это включает все обязанности, упомянутые в пункте а).
A33: 23 | B33: Зачет аванса | C33: Зачет аванса производится пропорционально остатку объема выполненных работ и рассчитывается на первое число каждого месяца
A34: 24 | B34: Дата получения стоимости материалов и работ от поставщиков и подрядчиков для формирования стоимости текущего КП | C34: ='Осн. параметры '!C8 -> 46232
A35: 25 | B35: Условия оплаты СМР | C35: 10 рабочих дней после подписания КС2 и КС3
A36: 26 | B36: Временные сети и подъездные пути | C36: Заказчик обязан предоставить в пределах строительной площадки точки подключения к временным сетям водоснабжения, электроснабжения и водоотведения с необходимой мощностью и производительностью для обеспечения бесперебойного снабжения на весь период строительства, а также обеспечить беспрепятственный доступ к подъездным путям для транспортировки материалов и оборудования. Заказчик несет ответственность за соответствие параметров временных сетей ТУ и подъездных путей нормативам, их работоспособность, а также за выполнение всех связанных с подключением, обслуживанием и демонтажем работ за свой счет.
A37: 27 | B37: Договор Генерального подряда | C37: Договор в редакции Заказчика с учётом протокола разногласий.
A38: 28 | B38: Перечень исполнительной документации | C38: Содержит подробный перечень исполнительной документации (Приложение №7), которая должна быть предоставлена при сдаче работ. Он включает различные виды документов, такие как журналы работ, акты освидетельствования скрытых и ответственных конструкций, исполнительные чертежи, паспорта и сертификаты соответствия на материалы и оборудование, а также приказы и квалификационные удостоверения ответственных лиц. Каждый документ указан с указанием его вида (оригинал, копия, электронный вид), а также типовое объединение документов по однотипным конструкциям и без указания физических объемов, за исключением сыпучих материалов.
B41: Приложения к Ключевым условиям:
B42: 1. Приложение №4. Методика определения стоимости основных ресурсов
B43: 2. Приложение №5. Базовая стоимость строительных материалов
B44: 3. Приложение №6. Руководство АО СУ-10 по технической эксплуатации зданий, сооружений, инженерных систем и технических средств
B45: 4. Приложение №7. Перечень исполнительной документации

Sheet Сущ. условия Подряд
A1: СУЩЕСТВЕННЫЕ УСЛОВИЯ ПОДРЯДА:
A3: № | B3: Сроки выполнения работ | C3: Предлагаемые условия СУ-10 | D3: Комментарии Заказчика
A4: 1 | B4: Цена Договора | C4: Твердая за единицу. Объемы - по факту.
A5: 2 | B5: Ед. измерения в сметной документации | C5: Ведомость объемов работ (физ. объемы)
A6: 3 | B6: Коммунальные платежи и содержание стройплощадки | C6: Коммунальные платежи входят в Цену Договора до Итогового акта
A7: 4 | B7: Авансы | C7: Общий аванс - 40% 1. 5% на аванс под БГ; 2. 35% по распред. письмам (фин. поручениям) на материалы без БГ в течение работ. Заказчик осуществляет оплату целевого аванса на основании счетов, выставленных как поставщиком Подрядчика, так и поставщикам Субподрядчика
A8: 5 | B8: Условия изменения договорной цены | C8: {=_xlfn.SWITCH('Осн. параметры '!C13,'Сущ. условия (текст)'!D35,'Сущ. условия (текст)'!E35,'Сущ. условия (текст)'!D36,'Сущ. условия (текст)'!E36)} -> В стоимости Работ учтен рост стоимости материалов 5%. В случае, если рыночная цена изменится по отношению к базовой стоимости материалов (БСМ) (Приложение №6), актуальной на 30.07.2026, более, чем на 5%, то с 6% будет проведен перерасчет стоимости ресурсов между Заказчиком и Генеральным подрядчиком по Методике, изложенной в Приложении №5. Данный процесс предусматривает согласование новых цен и оформление Протоколов изменений, которые могут повлечь за собой корректировку стоимости в рамках договора.
A9: 6 | B9: Компенсация роста стоимости материалов | C9: {=_xlfn.SWITCH('Осн. параметры '!C13,'Сущ. условия (текст)'!D35,'Сущ. условия (текст)'!F35,'Сущ. условия (текст)'!D36,'Сущ. условия (текст)'!F36)} -> 1. Методика удорожания/удешевления стоимости материалов, в БСМ бетон и арматура, коридор 5%. 2. Внесение изменений в П, РД, ТЗ, Ведомость объемов работ и Приложения к Договору. 3. По мере выхода РД, сверка/уточнение объемов, в случае увеличения/уменьшения - стороны подписывают ДС. 4. В случае изменения НДС, стоимость профинансированных (в т.ч. посредством оплаты авансовых платежей) работ рассчитывается по ставке НДС, действовавшей на дату финансирования соответствующих работ, а стоимость не профинансированных работ подлежит изменению с учетом новой ставки НДС посредством подписания дополнительного соглашения к настоящему Договору.
A10: 7 | B10: Сроки выполнения работ | C10: ='Сущ. условия (текст)'!E40 -> Срок выполнения работ составляет 24 мес. до Итогового Акта и 3 мес. на передачу объекта.
A11: 8 | B11: Банковские гарантии | C11: 1. БГ исполнения - не предоставляется 2. БГ на аванс - на аванс до 5% от Цены Договора 3. БГ гарантийного периода - не предоставляется
A12: 9 | B12: Гарантийные удержания | C12: ГУ - не предусмотрено
A13: 10 | B13: Гарантийный срок | C13: Гарантийный период на выполненные работы начинается с момента подписания итогового акта сдачи-приемки выполненных работ. Сроки гарантийного периода: ● Общестроительные работы - 36 месяцев
A14: 11 | B14: Окончательная приемка работ | C14: Итоговый Акт после окончания работ
A15: 12 | B15: Работы, не предусмотренные в данном Договоре
A19: 13 | B19: К вниманию Заказчика
A24: 14 | B24: Исполнительная документация | C24: Каникулы по ИД на 1 мес., кроме чек листов и 7-ми суточных лабораторных заключений. Исполнительная документация оформляется Подрядчиком в виде электронных документов в среде общих данных (СОД). В качестве СОД используется программный комплекс HARDROLLER.
A25: 15 | B25: Штрафные санкции для Подрядчика | C25: Общий лимит ответственности по неустойкам – 3% от Цены Работ. Перечень ключевых событий, за которые полагаются штрафы: 1. Завершение работ по монолиту подземной части - 100 000 руб/мес.; 2. Завершение работ по монолиту надземной части - 100 000 руб./мес.; 3. Завершение работ по кладке - 100 000 руб./мес.; 4. Завершение работ по кровле - 100 000 руб./мес.; 5. Итоговый акт - 100 000 руб./мес.; Все штрафы за сроки с 31 дня. Штрафы подлежат учету, но не удерживаются, при этом в случае окончания работ вовремя, вся сумма штрафов аннулируется. При этом под практическим завершением по каждому из Ключевых событий подразумевается выполнение подрядчиком работ в объеме, достаточном для выполнения последующих видов работ и начала их использования, с возможным наличием технологических проемов и отверстий, необходимых для осуществления прочих видов работ по Договору.
A26: 16 | B26: Условия с номинированными Материалами и начисления Подрядного процента: | C26: В случае удорожания/удешевления компенсировать разницу с учетом коэффициента отходов (раскрой, усушка, утряска) + 5% на рост стоимости материалов
A27: 17 | B27: Зачет аванса | C27: Зачет аванса производится пропорционально остатку объема выполненных работ и рассчитывается на первое число каждого месяца
A28: 18 | B28: Дата получения стоимости материалов и работ от поставщиков и подрядчиков для формирования стоимости текущего КП | C28: ='Осн. параметры '!C17 -> 46233
A29: 19 | B29: Условия оплаты СМР | C29: 10 рабочих дней после подписания КС2 и КС3
A30: 20 | B30: Временные сети и подъездные пути | C30: Заказчик обязан предоставить в пределах строительной площадки точки подключения к временным сетям водоснабжения, электроснабжения и водоотведения с необходимой мощностью и производительностью для обеспечения бесперебойного снабжения на весь период строительства, а также обеспечить беспрепятственный доступ к подъездным путям для транспортировки материалов и оборудования. Заказчик несет ответственность за соответствие параметров временных сетей ТУ и подъездных путей нормативам, их работоспособность, а также за выполнение всех связанных с подключением, обслуживанием и демонтажем работ за свой счет.
A31: 21 | B31: Договор Подряда | C31: Договор в редакции Заказчика с учётом протокола разногласий.
A32: 22 | B32: Перечень исполнительной документации | C32: Содержит подробный перечень исполнительной документации (Приложение №6), которая должна быть предоставлена при сдаче работ. Он включает различные виды документов, такие как журналы работ, акты освидетельствования скрытых и ответственных конструкций, исполнительные чертежи, паспорта и сертификаты соответствия на материалы и оборудование, а также приказы и квалификационные удостоверения ответственных лиц. Каждый документ указан с указанием его вида (оригинал, копия, электронный вид), а также типовое объединение документов по однотипным конструкциям и без указания физических объемов, за исключением сыпучих материалов.
B35: Приложения к Ключевым условиям:
B36: 1. Приложение №4. Методика определения стоимости основных ресурсов
B37: 2. Приложение №5. Базовая стоимость строительных материалов
B38: 3. Приложение №7. Перечень исполнительной документации

Sheet Сущ. условия  (текст)
E1: ГЕНПОДРЯД
E3: Компенсация роста стоимости материалов | F3: Условия изменения цены
D4: БСМ0% | E4: ="Компенсация роста стоимости материалов выполняется по следующему механизму: В стоимости Работ не учтен рост стоимости материалов. В случае, если рыночная цена изменится по отношению к базовой стоимости материалов (БСМ) (Приложение №5), актуальной на " & TEXT('Осн. параметры '!C8,"ДД.ММ.ГГГГ") & " года, будет проведен перерасчет стоимости ресурсов между Заказчиком и Генеральным подрядчиком по Методике, изложенной в Приложении №4. Данный процесс предусматривает согласование новых цен и оформление Протоколов изменений, " & "которые могут повлечь за собой корректировку стоимости в рамках договора." -> Компенсация роста стоимости материалов выполняется по следующему механизму: В стоимости Работ не учтен рост стоимости материалов. В случае, если рыночная цена изменится по отношению к базовой стоимости материалов (БСМ) (Приложение №5), актуальной на 29.07.2026 года, будет проведен перерасчет стоимости ресурсов между Заказчиком и Генеральным подрядчиком по Методике, изложенной в Приложении №4. Данный процесс предусматривает согласование новых цен и оформление Протоколов изменений, которые могут повлечь за собой корректировку стоимости в рамках договора. | F4: 1. Рост стоимости материалов более 0%. Компенсация производится с 1-ого процента. 2. Внесения Заказчиком по своей инициативе изменений в Проектную документацию и/или Рабочую документацию и/или Техническое задание и/или Дизайн проект, Вендор лист предусматривающих изменение объема, состава и/или содержания Работ и/или наименование материала. 3. В случае изменения ставки НДС, стоимость профинансированных (в т.ч. посредством оплаты авансовых платежей) работ рассчитывается по ставке НДС, действовавшей на дату финансирования соответствующих работ, а стоимость не профинансированных работ подлежит изменению с учетом новой ставки НДС посредством подписания дополнительного соглашения к настоящему Договору.
D5: БСМ5% | E5: ="Компенсация роста стоимости материалов выполняется по следующему механизму: В стоимости Работ учтен рост стоимости материалов 5%. В случае, если рыночная цена изменится по отношению к базовой стоимости материалов (БСМ) (Приложение №5), актуальной на " & TEXT('Осн. параметры '!C8,"ДД.ММ.ГГГГ") & " года, более, чем на 5%, то с 6% будет проведен перерасчет стоимости ресурсов между Заказчиком и Генеральным подрядчиком по Методике, изложенной в Приложении №4. " & "Данный процесс предусматривает согласование новых цен и оформление Протоколов изменений, которые могут повлечь за собой корректировку стоимости в рамках договора." -> Компенсация роста стоимости материалов выполняется по следующему механизму: В стоимости Работ учтен рост стоимости материалов 5%. В случае, если рыночная цена изменится по отношению к базовой стоимости материалов (БСМ) (Приложение №5), актуальной на 29.07.2026 года, более, чем на 5%, то с 6% будет проведен перерасчет стоимости ресурсов между Заказчиком и Генеральным подрядчиком по Методике, изложенной в Приложении №4. Данный процесс предусматривает согласование новых цен и оформление Протоколов изменений, которые могут повлечь за собой корректировку стоимости в рамках договора. | F5: 1. Рост стоимости материалов более 5%. Компенсация производится с 6-ого процента. 2. Внесения Заказчиком по своей инициативе изменений в Проектную документацию и/или Рабочую документацию и/или Техническое задание и/или Дизайн проект, Вендор лист предусматривающих изменение объема, состава и/или содержания Работ и/или наименование материала. 3. В случае изменения ставки НДС, стоимость профинансированных (в т.ч. посредством оплаты авансовых платежей) работ рассчитывается по ставке НДС, действовавшей на дату финансирования соответствующих работ, а стоимость не профинансированных работ подлежит изменению с учетом новой ставки НДС посредством подписания дополнительного соглашения к настоящему Договору.
D6: Инфляция 0% | E6: Компенсация роста стоимости материалов выполняется по следующиму механизму: Механизм компенсации стоимости Работ заключается в индексации цены договора на уровень накопленной инфляции, превышающей 0%. Накопленная инфляция рассчитывается на основе ежемесячных индексов цен на строительные материалы, публикуемых Росстатом, начиная с даты первой подачи КП. Индексация применяется к общей стоимости, выполненных и принятых Работ по актам КС-2 , начиная с месяца в котором накопленная инфляция превысила 0%. | F6: ="1. Компенсация предусматривает индексацию стоимости фактически выполненных и принятых Работ на уровень накопленной инфляции по Росстату, начиная с " & TEXT('Осн. параметры '!C8, "ММ.ГГГГ ""г.""") & " 2. Внесения Заказчиком по своей инициативе изменений в " & "Проектную документацию и/или Рабочую документацию и/или Техническое задание и/или Дизайн проект, Вендор лист предусматривающих изменение объема, состава и/или содержания Работ и/или наименование материала. " & " 3. В случае изменения ставки НДС, стоимость профинансированных (в т.ч. посредством оплаты авансовых платежей) работ рассчитывается по ставке НДС, действовавшей на дату " & "финансирования соответствующих работ, а стоимость не профинансированных работ подлежит изменению с учетом новой ставки НДС " & "посредством подписания дополнительного соглашения к настоящему Договору" -> 1. Компенсация предусматривает индексацию стоимости фактически выполненных и принятых Работ на уровень накопленной инфляции по Росстату, начиная с 07.2026 г. 2. Внесения Заказчиком по своей инициативе изменений в Проектную документацию и/или Рабочую документацию и/или Техническое задание и/или Дизайн проект, Вендор лист предусматривающих изменение объема, состава и/или содержания Работ и/или наименование материала. 3. В случае изменения ставки НДС, стоимость профинансированных (в т.ч. посредством оплаты авансовых платежей) работ рассчитывается по ставке НДС, действовавшей на дату финансирования соответствующих работ, а стоимость не профинансированных работ подлежит изменению с учетом новой ставки НДС посредством подписания дополнительного соглашения к настоящему Договору
D7: Инфляция 5% | E7: Компенсация роста стоимости материалов выполняется по следующиму механизму: Механизм компенсации стоимости Работ заключается в индексации цены договора на уровень накопленной инфляции, превышающей 5%. Накопленная инфляция рассчитывается на основе ежемесячных индексов цен на строительные материалы, публикуемых Росстатом, начиная с даты первой подачи КП. Индексация применяется к общей стоимости, выполненных и принятых Работ по актам КС-2 , начиная с месяца в котором накопленная инфляция превысила 5%. | F7: ="1. Компенсация предусматривает индексацию стоимости фактически выполненных и принятых Работ на уровень накопленной инфляции по Росстату, превышающей 5%, начиная с " & TEXT('Осн. параметры '!C8, "ММ.ГГГГ ""г.""") & " 2. Внесения Заказчиком по своей инициативе изменений в " & "Проектную документацию и/или Рабочую документацию и/или Техническое задание и/или Дизайн проект, Вендор лист предусматривающих изменение объема, состава и/или содержания Работ и/или наименование материала. " & " 3. В случае изменения ставки НДС, стоимость профинансированных (в т.ч. посредством оплаты авансовых платежей) работ рассчитывается по ставке НДС, действовавшей на дату " & "финансирования соответствующих работ, а стоимость не профинансированных работ подлежит изменению с учетом новой ставки НДС " & "посредством подписания дополнительного соглашения к настоящему Договору" -> 1. Компенсация предусматривает индексацию стоимости фактически выполненных и принятых Работ на уровень накопленной инфляции по Росстату, превышающей 5%, начиная с 07.2026 г. 2. Внесения Заказчиком по своей инициативе изменений в Проектную документацию и/или Рабочую документацию и/или Техническое задание и/или Дизайн проект, Вендор лист предусматривающих изменение объема, состава и/или содержания Работ и/или наименование материала. 3. В случае изменения ставки НДС, стоимость профинансированных (в т.ч. посредством оплаты авансовых платежей) работ рассчитывается по ставке НДС, действовавшей на дату финансирования соответствующих работ, а стоимость не профинансированных работ подлежит изменению с учетом новой ставки НДС посредством подписания дополнительного соглашения к настоящему Договору
D8: Инфляция 0% + БСМ 0% | E8: Компенсация роста стоимости материалов выполняется по следующиму механизму: Механизм компенсации стоимости Работ заключается в индексации цены договора на уровень накопленной инфляции, превышающей 0%. Накопленная инфляция рассчитывается на основе ежемесячных индексов цен на строительные материалы, публикуемых Росстатом, начиная с даты первой подачи КП. Индексация применяется к общей стоимости, выполненных и принятых Работ по актам КС-2 , начиная с месяца в котором накопленная инфляция превысила 0%. В случае значительного роста стоимости волатильных материалов (перечень БСМ - Приложение №5), который не перекрывается коэффициентом инфляции, Генподрядчик может подать отдельный расчёт удорожания, согласно методике (Приложение №4), корректируя его с учётом накопленного процента инфляции. Подрядчик самостоятельно рассчитывает ежемесячно накопленную инфляцию и направляет расчёт заказчику для утверждения. Заказчик рассматривает расчёт и, при отсутствии замечаний, подписывает его, после чего стороны заключают дополнительное соглашение об изменении цены договора, но не чаще 1-ого раза в квартал. | F8: ="1. Рост стоимости материалов БСМ более 0%. Компенсация производится с 1-ого процента. 2. Компенсация предусматривает индексацию стоимости фактически выполненных и принятых Работ на уровень накопленной инфляции по Росстату, начиная с " & TEXT('Осн. параметры '!C8, "ММ.ГГГГ ""г.""") & ", без учета материалов БСМ. " & " 3. Внесения Заказчиком по своей инициативе изменений в Проектную документацию и/или Рабочую документацию и/или Техническое задание и/или Дизайн проект, " & "Вендор лист предусматривающих изменение объема, состава и/или содержания Работ и/или наименование материала. 4. В случае изменения ставки НДС, " & "стоимость профинансированных (в т.ч. посредством оплаты авансовых платежей) работ рассчитывается по ставке НДС, действовавшей на дату " & "финансирования соответствующих работ, а стоимость не профинансированных работ подлежит изменению с учетом новой ставки НДС " & "посредством подписания дополнительного соглашения к настоящему Договору" -> 1. Рост стоимости материалов БСМ более 0%. Компенсация производится с 1-ого процента. 2. Компенсация предусматривает индексацию стоимости фактически выполненных и принятых Работ на уровень накопленной инфляции по Росстату, начиная с 07.2026 г., без учета материалов БСМ. 3. Внесения Заказчиком по своей инициативе изменений в Проектную документацию и/или Рабочую документацию и/или Техническое задание и/или Дизайн проект, Вендор лист предусматривающих изменение объема, состава и/или содержания Работ и/или наименование материала. 4. В случае изменения ставки НДС, стоимость профинансированных (в т.ч. посредством оплаты авансовых платежей) работ рассчитывается по ставке НДС, действовавшей на дату финансирования соответствующих работ, а стоимость не профинансированных работ подлежит изменению с учетом новой ставки НДС посредством подписания дополнительного соглашения к настоящему Договору
D9: Инфляция 0% + БСМ 5% | E9: Компенсация роста стоимости материалов выполняется по следующиму механизму: Механизм компенсации стоимости Работ заключается в индексации цены договора на уровень накопленной инфляции, превышающей 0%. Накопленная инфляция рассчитывается на основе ежемесячных индексов цен на строительные материалы, публикуемых Росстатом, начиная с даты первой подачи КП. Индексация применяется к общей стоимости, выполненных и принятых Работ по актам КС-2 , начиная с месяца в котором накопленная инфляция превысила 0%. В случае значительного роста стоимости волатильных материалов (перечень БСМ - Приложение №5), который не перекрывается коэффициентом инфляции, Генподрядчик может подать отдельный расчёт удорожания, согласно методике (Приложение №4), корректируя его с учётом накопленного процента инфляции. Подрядчик самостоятельно рассчитывает ежемесячно накопленную инфляцию и направляет расчёт заказчику для утверждения. Заказчик рассматривает расчёт и, при отсутствии замечаний, подписывает его, после чего стороны заключают дополнительное соглашение об изменении цены договора, но не чаще 1-ого раза в квартал. | F9: ="1. Рост стоимости материалов БСМ более 5%. Компенсация производится с 6-ого процента. 2. Компенсация предусматривает индексацию стоимости фактически выполненных и принятых Работ на уровень накопленной инфляции по Росстату, начиная с " & TEXT('Осн. параметры '!C8, "ММ.ГГГГ ""г.""") & ", без учета материалов БСМ. " & " 3. Внесения Заказчиком по своей инициативе изменений в Проектную документацию и/или Рабочую документацию и/или Техническое задание и/или Дизайн проект, " & "Вендор лист предусматривающих изменение объема, состава и/или содержания Работ и/или наименование материала. " & " 4. В случае изменения ставки НДС, стоимость профинансированных (в т.ч. посредством оплаты авансовых платежей) работ рассчитывается по ставке НДС, " & "действовавшей на дату финансирования соответствующих работ, а стоимость не профинансированных работ подлежит изменению с учетом новой ставки НДС " & "посредством подписания дополнительного соглашения к настоящему Договору" -> 1. Рост стоимости материалов БСМ более 5%. Компенсация производится с 6-ого процента. 2. Компенсация предусматривает индексацию стоимости фактически выполненных и принятых Работ на уровень накопленной инфляции по Росстату, начиная с 07.2026 г., без учета материалов БСМ. 3. Внесения Заказчиком по своей инициативе изменений в Проектную документацию и/или Рабочую документацию и/или Техническое задание и/или Дизайн проект, Вендор лист предусматривающих изменение объема, состава и/или содержания Работ и/или наименование материала. 4. В случае изменения ставки НДС, стоимость профинансированных (в т.ч. посредством оплаты авансовых платежей) работ рассчитывается по ставке НДС, действовавшей на дату финансирования соответствующих работ, а стоимость не профинансированных работ подлежит изменению с учетом новой ставки НДС посредством подписания дополнительного соглашения к настоящему Договору
D10: Инфляция 5% + БСМ 0% | E10: Компенсация роста стоимости материалов выполняется по следующиму механизму: Механизм компенсации стоимости Работ заключается в индексации цены договора на уровень накопленной инфляции, превышающей 5%. Накопленная инфляция рассчитывается на основе ежемесячных индексов цен на строительные материалы, публикуемых Росстатом, начиная с даты первой подачи КП. Индексация применяется к общей стоимости, выполненных и принятых Работ по актам КС-2 , начиная с месяца в котором накопленная инфляция превысила 5%. В случае значительного роста стоимости волатильных материалов (перечень БСМ - Приложение №5), который не перекрывается коэффициентом инфляции, Генподрядчик может подать отдельный расчёт удорожания, согласно методике (Приложение №4), корректируя его с учётом накопленного процента инфляции. Подрядчик самостоятельно рассчитывает ежемесячно накопленную инфляцию и направляет расчёт заказчику для утверждения. Заказчик рассматривает расчёт и, при отсутствии замечаний, подписывает его, после чего стороны заключают дополнительное соглашение об изменении цены договора, но не чаще 1-ого раза в квартал. | F10: ="1. Рост стоимости материалов БСМ более 0%. Компенсация производится с 1-ого процента." & CHAR(10) & "2. Компенсация предусматривает индексацию стоимости фактически выполненных и принятых Работ на уровень накопленной инфляции по Росстату, превышающей 5%, начиная с " & TEXT('Осн. параметры '!C8, "ММ.ГГГГ ""г.""") & ", без учета материалов БСМ." & CHAR(10) & "3. Внесения Заказчиком по своей инициативе изменений в Проектную документацию и/или Рабочую документацию и/или Техническое задание и/или Дизайн проект, " & "Вендор лист предусматривающих изменение объема, состава и/или содержания Работ и/или наименование материала." & CHAR(10) & "4. В случае изменения ставки НДС, стоимость профинансированных (в т.ч. посредством оплаты авансовых платежей) работ рассчитывается по ставке НДС, " & "действовавшей на дату финансирования соответствующих работ, а стоимость не профинансированных работ подлежит изменению с учетом новой ставки НДС посредством подписания " & "дополнительного соглашения к настоящему Договору" -> 1. Рост стоимости материалов БСМ более 0%. Компенсация производится с 1-ого процента. 2. Компенсация предусматривает индексацию стоимости фактически выполненных и принятых Работ на уровень накопленной инфляции по Росстату, превышающей 5%, начиная с 07.2026 г., без учета материалов БСМ. 3. Внесения Заказчиком по своей инициативе изменений в Проектную документацию и/или Рабочую документацию и/или Техническое задание и/или Дизайн проект, Вендор лист предусматривающих изменение объема, состава и/или содержания Работ и/или наименование материала. 4. В случае изменения ставки НДС, стоимость профинансированных (в т.ч. посредством оплаты авансовых платежей) работ рассчитывается по ставке НДС, действовавшей на дату финансирования соответствующих работ, а стоимость не профинансированных работ подлежит изменению с учетом новой ставки НДС посредством подписания дополнительного соглашения к настоящему Договору
D11: Инфляция 5% + БСМ 5% | E11: Компенсация роста стоимости материалов выполняется по следующиму механизму: Механизм компенсации стоимости Работ заключается в индексации цены договора на уровень накопленной инфляции, превышающей 5%. Накопленная инфляция рассчитывается на основе ежемесячных индексов цен на строительные материалы, публикуемых Росстатом, начиная с даты первой подачи КП. Индексация применяется к общей стоимости, выполненных и принятых Работ по актам КС-2 , начиная с месяца в котором накопленная инфляция превысила 5%. В случае значительного роста стоимости волатильных материалов (перечень БСМ - Приложение №5), который не перекрывается коэффициентом инфляции, Генподрядчик может подать отдельный расчёт удорожания, согласно методике (Приложение №4), корректируя его с учётом накопленного процента инфляции. Подрядчик самостоятельно рассчитывает ежемесячно накопленную инфляцию и направляет расчёт заказчику для утверждения. Заказчик рассматривает расчёт и, при отсутствии замечаний, подписывает его, после чего стороны заключают дополнительное соглашение об изменении цены договора, но не чаще 1-ого раза в квартал. | F11: ="1. Рост стоимости материалов БСМ более 5%. Компенсация производится с 6-ого процента." & CHAR(10) & "2. Компенсация предусматривает индексацию стоимости фактически выполненных и принятых Работ на уровень накопленной инфляции по Росстату, превышающей 5%, начиная с " & TEXT('Осн. параметры '!C8, "ММ.ГГГГ ""г.""") & ", без учета материалов БСМ." & CHAR(10) & "3. Внесения Заказчиком по своей инициативе изменений в Проектную документацию и/или Рабочую документацию и/или Техническое задание и/или Дизайн проект, " & "Вендор лист предусматривающих изменение объема, состава и/или содержания Работ и/или наименование материала." & CHAR(10) & "4. В случае изменения ставки НДС, стоимость профинансированных (в т.ч. посредством оплаты авансовых платежей) работ рассчитывается по ставке НДС, " & "действовавшей на дату финансирования соответствующих работ, а стоимость не профинансированных работ подлежит изменению с учетом новой ставки НДС посредством подписания " & "дополнительного соглашения к настоящему Договору" -> 1. Рост стоимости материалов БСМ более 5%. Компенсация производится с 6-ого процента. 2. Компенсация предусматривает индексацию стоимости фактически выполненных и принятых Работ на уровень накопленной инфляции по Росстату, превышающей 5%, начиная с 07.2026 г., без учета материалов БСМ. 3. Внесения Заказчиком по своей инициативе изменений в Проектную документацию и/или Рабочую документацию и/или Техническое задание и/или Дизайн проект, Вендор лист предусматривающих изменение объема, состава и/или содержания Работ и/или наименование материала. 4. В случае изменения ставки НДС, стоимость профинансированных (в т.ч. посредством оплаты авансовых платежей) работ рассчитывается по ставке НДС, действовавшей на дату финансирования соответствующих работ, а стоимость не профинансированных работ подлежит изменению с учетом новой ставки НДС посредством подписания дополнительного соглашения к настоящему Договору
D14: Аванс 30% | E14: Общий аванс - 30%. Допустимо 5% на аванс под БГ и 25% по распред. письмам за материалы без БГ. Аванс 5% выплачиваются на обычный расчетный счет с предоставлением Банковской гарантии.
D15: Аванс 40% | E15: Общий аванс - 40%. Допустимо 5% на аванс под БГ и 35% по распред. письмам за материалы без БГ. Аванс 5% выплачиваются на обычный расчетный счет с предоставлением Банковской гарантии.
D16: Донстрой | E16: Общий аванс – 40-60%. Допустимо до 10% без БГ на расчетный счет Генподрядчика и 30-50% по распред. письмам поставщикам/подрядчикам.
D17: Иной
D20: Срок строительства | E20: ="Срок выполнения работ составляет " & 'Осн. параметры '!C6 & " мес. до оформления Акта ЗОС и " & 'Осн. параметры '!C7 & " мес. на передачу объекта и подписание Итогового акта №3" -> Срок выполнения работ составляет 24 мес. до оформления Акта ЗОС и 3 мес. на передачу объекта и подписание Итогового акта №3
E21: Срок выполнения работ составляет
E22: ='Осн. параметры '!C6 -> 24
E23: мес. до оформления Акта ЗОС и
E24: ='Осн. параметры '!C7 -> 3
E25: мес. на передачу объекта и подписание Итогового акта №3
E26: =CONCATENATE(E21,E22," ",E23," ",E24," ",E25) -> Срок выполнения работ составляет 24 мес. до оформления Акта ЗОС и 3 мес. на передачу объекта и подписание Итогового акта №3
E31: Коробка
D35: БСМ0% | E35: ="В стоимости Работ учтен рост стоимости материалов 0%. В случае, если рыночная цена изменится по отношению к базовой стоимости материалов (БСМ) (Приложение №6), актуальной на " & TEXT('Осн. параметры '!C17,"ДД.ММ.ГГГГ") & ", более, чем на 0%, то с 1% будет проведен перерасчет стоимости ресурсов между Заказчиком и Генеральным подрядчиком по Методике, изложенной в Приложении №5. Данный процесс предусматривает согласование новых цен и оформление " & " Протоколов изменений, которые могут повлечь за собой корректировку стоимости в рамках договора." -> В стоимости Работ учтен рост стоимости материалов 0%. В случае, если рыночная цена изменится по отношению к базовой стоимости материалов (БСМ) (Приложение №6), актуальной на 30.07.2026, более, чем на 0%, то с 1% будет проведен перерасчет стоимости ресурсов между Заказчиком и Генеральным подрядчиком по Методике, изложенной в Приложении №5. Данный процесс предусматривает согласование новых цен и оформление Протоколов изменений, которые могут повлечь за собой корректировку стоимости в рамках договора. | F35: 1. Методика удорожания/удешевления стоимости материалов, в БСМ бетон и арматура, коридор 0%. 2. Внесение изменений в П, РД, ТЗ, Ведомость объемов работ и Приложения к Договору. 3. По мере выхода РД, сверка/уточнение объемов, в случае увеличения/уменьшения - стороны подписывают ДС. 4. В случае изменения НДС, стоимость профинансированных (в т.ч. посредством оплаты авансовых платежей) работ рассчитывается по ставке НДС, действовавшей на дату финансирования соответствующих работ, а стоимость не профинансированных работ подлежит изменению с учетом новой ставки НДС посредством подписания дополнительного соглашения к настоящему Договору.
D36: БСМ5% | E36: ="В стоимости Работ учтен рост стоимости материалов 5%. В случае, если рыночная цена изменится по отношению к базовой стоимости материалов (БСМ) (Приложение №6), актуальной на " & TEXT('Осн. параметры '!C17,"ДД.ММ.ГГГГ") & ", более, чем на 5%, то с 6% будет проведен перерасчет стоимости ресурсов между Заказчиком и Генеральным подрядчиком по Методике, изложенной в Приложении №5. Данный процесс предусматривает согласование новых цен и оформление " & " Протоколов изменений, которые могут повлечь за собой корректировку стоимости в рамках договора." -> В стоимости Работ учтен рост стоимости материалов 5%. В случае, если рыночная цена изменится по отношению к базовой стоимости материалов (БСМ) (Приложение №6), актуальной на 30.07.2026, более, чем на 5%, то с 6% будет проведен перерасчет стоимости ресурсов между Заказчиком и Генеральным подрядчиком по Методике, изложенной в Приложении №5. Данный процесс предусматривает согласование новых цен и оформление Протоколов изменений, которые могут повлечь за собой корректировку стоимости в рамках договора. | F36: 1. Методика удорожания/удешевления стоимости материалов, в БСМ бетон и арматура, коридор 5%. 2. Внесение изменений в П, РД, ТЗ, Ведомость объемов работ и Приложения к Договору. 3. По мере выхода РД, сверка/уточнение объемов, в случае увеличения/уменьшения - стороны подписывают ДС. 4. В случае изменения НДС, стоимость профинансированных (в т.ч. посредством оплаты авансовых платежей) работ рассчитывается по ставке НДС, действовавшей на дату финансирования соответствующих работ, а стоимость не профинансированных работ подлежит изменению с учетом новой ставки НДС посредством подписания дополнительного соглашения к настоящему Договору.
D40: Срок строительства | E40: ="Срок выполнения работ составляет " & 'Осн. параметры '!C15 & " мес. до Итогового Акта и " & 'Осн. параметры '!C16 & " мес. на передачу объекта." -> Срок выполнения работ составляет 24 мес. до Итогового Акта и 3 мес. на передачу объекта. | F40: Срок выполнения работ составляет 34 месяца до Итогового Акта и 2 месяца на передачу объекта
E41: Срок выполнения работ составляет
E42: ='Осн. параметры '!C26 -> 0
E43: мес. до оформления Акта ЗОС и
E44: ='Осн. параметры '!C27 -> 0
E45: мес. на передачу объекта и подписание Итогового акта №3
E46: =CONCATENATE(E41,E42," ",E43," ",E44," ",E45) -> Срок выполнения работ составляет 0 мес. до оформления Акта ЗОС и 0 мес. на передачу объекта и подписание Итогового акта №3
